agentic_social_server-1.0.0.dist-info/licenses/LICENSE
social_server/__init__.py
social_server/app.py
social_server/core/__init__.py
social_server/core/paths.py
social_server/core/simple_auth.py
social_server/modules/__init__.py
social_server/modules/ai_personas.py
social_server/modules/feed_generator.py
social_server/modules/gamma_burst_insights.md
social_server/modules/social_models.py
social_server/modules/generate_social_feed/__init__.py
social_server/modules/generate_social_feed/feed_generator.py
social_server/modules/generate_social_feed/social_models.py
social_server/pages/22_AI_Social_Feed.py
social_server/pages/23_Profile_Home.py
social_server/pages/24_Login_Register.py
social_server/pages/__init__.py
agentic_social_server-1.0.0.dist-info/METADATA
agentic_social_server-1.0.0.dist-info/WHEEL
agentic_social_server-1.0.0.dist-info/entry_points.txt
agentic_social_server-1.0.0.dist-info/top_level.txt
agentic_social_server-1.0.0.dist-info/RECORD
