Metadata-Version: 2.4
Name: agentic-social-server
Version: 1.0.0
Summary: AI-powered social media platform with 4-factor neurochemical optimization for book lovers
Author-email: Nimble Research Collective <contact@nimbleresearch.org>
Maintainer-email: Nimble Research Collective <contact@nimbleresearch.org>
License: MIT
Project-URL: Homepage, https://github.com/nimble-research/agentic-social-server
Project-URL: Documentation, https://github.com/nimble-research/agentic-social-server/blob/main/README.md
Project-URL: Repository, https://github.com/nimble-research/agentic-social-server
Project-URL: Bug Tracker, https://github.com/nimble-research/agentic-social-server/issues
Project-URL: Changelog, https://github.com/nimble-research/agentic-social-server/blob/main/CHANGELOG.md
Keywords: ai,social-media,neuroscience,machine-learning,books,neurochemical-optimization,personas,streamlit,education
Classifier: Development Status :: 4 - Beta
Classifier: Intended Audience :: Developers
Classifier: Intended Audience :: Education
Classifier: Intended Audience :: Science/Research
Classifier: License :: OSI Approved :: MIT License
Classifier: Operating System :: OS Independent
Classifier: Programming Language :: Python :: 3
Classifier: Programming Language :: Python :: 3.12
Classifier: Programming Language :: Python :: 3.13
Classifier: Topic :: Communications :: Chat
Classifier: Topic :: Education
Classifier: Topic :: Internet :: WWW/HTTP :: Dynamic Content
Classifier: Topic :: Scientific/Engineering :: Artificial Intelligence
Classifier: Topic :: Software Development :: Libraries :: Python Modules
Requires-Python: >=3.12
License-File: LICENSE
Requires-Dist: streamlit>=1.28.0
Requires-Dist: nimble-llm-caller>=0.1.0
Requires-Dist: pandas>=1.5.0
Requires-Dist: python-dateutil>=2.8.0
Requires-Dist: pydantic>=2.0.0
Requires-Dist: bcrypt>=4.3.0
Provides-Extra: dev
Requires-Dist: pytest>=7.0.0; extra == "dev"
Requires-Dist: pytest-cov>=4.0.0; extra == "dev"
Requires-Dist: black>=23.0.0; extra == "dev"
Requires-Dist: isort>=5.12.0; extra == "dev"
Requires-Dist: flake8>=6.0.0; extra == "dev"
Requires-Dist: mypy>=1.0.0; extra == "dev"
Provides-Extra: docs
Requires-Dist: sphinx>=6.0.0; extra == "docs"
Requires-Dist: sphinx-rtd-theme>=1.2.0; extra == "docs"
Provides-Extra: academic
Requires-Dist: jupyter>=1.0.0; extra == "academic"
Requires-Dist: matplotlib>=3.7.0; extra == "academic"
Requires-Dist: seaborn>=0.12.0; extra == "academic"
Requires-Dist: scipy>=1.10.0; extra == "academic"
Dynamic: license-file
